{
    "shoulder_pan": {
        "id": 1,
        "drive_mode": 0,
        "homing_offset": 400,
        "range_min": 750,
        "range_max": 3463
    },
    "shoulder_lift": {
        "id": 2,
        "drive_mode": 0,
        "homing_offset": 1867,
        "range_min": 234,
        "range_max": 2547
    },
    "elbow_flex": {
        "id": 3,
        "drive_mode": 0,
        "homing_offset": 1829,
        "range_min": 150,
        "range_max": 2386
    },
    "wrist_flex": {
        "id": 4,
        "drive_mode": 0,
        "homing_offset": 772,
        "range_min": 0,
        "range_max": 4095
    },
    "wrist_roll": {
        "id": 5,
        "drive_mode": 0,
        "homing_offset": 1787,
        "range_min": 0,
        "range_max": 4095
    },
    "gripper": {
        "id": 6,
        "drive_mode": 0,
        "homing_offset": 832,
        "range_min": 2016,
        "range_max": 3521
    }
}